sqlglider/__init__.py
sqlglider/_version.py
sqlglider/cli.py
sqlglider/global_models.py
sqlglider/catalog/__init__.py
sqlglider/catalog/base.py
sqlglider/catalog/databricks.py
sqlglider/catalog/registry.py
sqlglider/dissection/__init__.py
sqlglider/dissection/analyzer.py
sqlglider/dissection/formatters.py
sqlglider/dissection/models.py
sqlglider/graph/__init__.py
sqlglider/graph/builder.py
sqlglider/graph/formatters.py
sqlglider/graph/merge.py
sqlglider/graph/models.py
sqlglider/graph/query.py
sqlglider/graph/serialization.py
sqlglider/lineage/__init__.py
sqlglider/lineage/analyzer.py
sqlglider/lineage/formatters.py
sqlglider/schema/__init__.py
sqlglider/schema/extractor.py
sqlglider/templating/__init__.py
sqlglider/templating/base.py
sqlglider/templating/jinja.py
sqlglider/templating/registry.py
sqlglider/templating/variables.py
sqlglider/utils/__init__.py
sqlglider/utils/config.py
sqlglider/utils/file_utils.py
sqlglider/utils/schema.py
sql_glider-0.1.20.dist-info/METADATA
sql_glider-0.1.20.dist-info/WHEEL
sql_glider-0.1.20.dist-info/entry_points.txt
sql_glider-0.1.20.dist-info/licenses/LICENSE
sql_glider-0.1.20.dist-info/RECORD
