Metadata-Version: 2.4
Name: sql-glider
Version: 0.1.20
Summary: SQL Utility Toolkit for better understanding, use, and governance of your queries in a native environment.
Project-URL: Homepage, https://github.com/rycowhi/sql-glider/
Project-URL: Repository, https://github.com/rycowhi/sql-glider/
Project-URL: Documentation, https://github.com/rycowhi/sql-glider/
Project-URL: Issues, https://github.com/rycowhi/sql-glider/issues
Author-email: Ryan Whitcomb <ryankwhitcomb@gmail.com>
License-Expression: Apache-2.0
License-File: LICENSE
Keywords: data-governance,data-lineage,lineage,sql,sqlglot
Classifier: Development Status :: 3 - Alpha
Classifier: Intended Audience :: Developers
Classifier: License :: OSI Approved :: Apache Software License
Classifier: Operating System :: OS Independent
Classifier: Programming Language :: Python :: 3 :: Only
Classifier: Programming Language :: SQL
Classifier: Topic :: Database
Classifier: Topic :: Software Development :: Libraries :: Python Modules
Classifier: Typing :: Typed
Requires-Python: >=3.11
Requires-Dist: jinja2>=3.0.0
Requires-Dist: pydantic>=2.0.0
Requires-Dist: rich>=13.0.0
Requires-Dist: rustworkx>=0.15.0
Requires-Dist: sqlglot[rs]>=25.0.0
Requires-Dist: typer>=0.9.0
Provides-Extra: databricks
Requires-Dist: databricks-sdk>=0.20.0; extra == 'databricks'
